langevaluate/__init__.py
langevaluate/config/__init__.py
langevaluate/config/evaluation_config.py
langevaluate/config/model_config.py
langevaluate/llmdataset/__init__.py
langevaluate/llmdataset/dataset.py
langevaluate/llmfactory/__init__.py
langevaluate/llmfactory/base_factory.py
langevaluate/llmfactory/llmfactory.py
langevaluate/llmresult/__init__.py
langevaluate/llmresult/result.py
langevaluate/llmtestcase/__init__.py
langevaluate/llmtestcase/llmtestcase.py
langevaluate/metrics/__init__.py
langevaluate/metrics/base_metric.py
langevaluate/metrics/base_template.py
langevaluate/metrics/arena/__init__.py
langevaluate/metrics/arena/arena_metric.py
langevaluate/metrics/arena/arena_template.py
langevaluate/metrics/judge/__init__.py
langevaluate/metrics/judge/judge_metric.py
langevaluate/metrics/judge/judge_template.py
langevaluate/metrics/mcq_choice/__init__.py
langevaluate/metrics/mcq_choice/mcq_metric.py
langevaluate/metrics/mcq_choice/mcq_template.py
langevaluate/metrics/score/__init__.py
langevaluate/metrics/score/score.py
langevaluate/metrics/score/score_template.py
langevaluate/metrics/summary_judge/__init__.py
langevaluate/metrics/summary_judge/summary_judge_metric.py
langevaluate/metrics/summary_judge/summary_judge_template.py
langevaluate/prompt_storage/__init__.py
langevaluate/prompt_storage/arena_prompt.toml
langevaluate/prompt_storage/clinical_summary_prompt.toml
langevaluate/prompt_storage/judge_prompt.toml
langevaluate/prompt_storage/mcq_choice_prompt.toml
langevaluate/prompt_storage/medical_evaluate_prompt.toml
langevaluate/prompt_storage/query_prompt.toml
langevaluate/quantiative_metrics/__init__.py
langevaluate/quantiative_metrics/bertscore.py
langevaluate/quantiative_metrics/efficientscore.py
langevaluate/quantiative_metrics/fairnessscore.py
langevaluate/quantiative_metrics/icdscore.py
langevaluate/quantiative_metrics/medconscore.py
langevaluate/utils/__init__.py
langevaluate/utils/utils.py
langevaluate-0.2.14.dist-info/METADATA
langevaluate-0.2.14.dist-info/WHEEL
langevaluate-0.2.14.dist-info/licenses/LICENSE
langevaluate-0.2.14.dist-info/RECORD
