Metadata-Version: 2.4
Name: langevaluate
Version: 0.2.14
Summary: LLM 기반의 자동 평가 시스템
Project-URL: Homepage, https://github.com/JINAILAB/langmetrics
Project-URL: Bug Tracker, https://github.com/JINAILAB/langmetrics/issues
Author-email: JIN PARK <nwirandx@gmail.com>
License: MIT
License-File: LICENSE
Keywords: LLM,NLP,benchmarks,evaluation,langchain
Classifier: License :: OSI Approved :: MIT License
Classifier: Operating System :: OS Independent
Classifier: Programming Language :: Python :: 3
Requires-Python: ==3.10.*
Requires-Dist: aiolimiter<=1.4.0,>=1.0.0
Requires-Dist: bert-score>=0.3.12
Requires-Dist: datasets<=4.3.0,>=3.0.0
Requires-Dist: langchain-anthropic>=0.3
Requires-Dist: langchain-community<0.4,>=0.3
Requires-Dist: langchain-deepseek-official>=0.1
Requires-Dist: langchain-google-genai>=0.1.0
Requires-Dist: langchain-openai>=0.3
Requires-Dist: langchain<0.4,>=0.3
Requires-Dist: numpy
Requires-Dist: pandas<2.5.0,>=2.0.0
Requires-Dist: polars<=1.40.0,>=1.21.0
Requires-Dist: python-dotenv<=1.2.0,>=1.0.0
Requires-Dist: rich>=13.0.0
Requires-Dist: scipy>=1.15.0
Requires-Dist: spacy>=3.4.4
Requires-Dist: toml>=0.10.0
Requires-Dist: tomlkit>=0.12.0
Provides-Extra: dev
Requires-Dist: ipykernel>=6.0.0; extra == 'dev'
Requires-Dist: pytest-asyncio>=0.21.1; extra == 'dev'
Requires-Dist: pytest-cov>=4.1.0; extra == 'dev'
Requires-Dist: pytest>=7.4.0; extra == 'dev'
